<messagebundle>
<msg name="hello">مرحباً</msg>
<msg name="welcome_to_golab">أهلاً بك في Go-Lab</msg>
<msg name="not_space_owner"> ست مالك(ة) لهذة المساحة. التغيير في ترتيب التطبيقات لن يُحفّظ </msg>
<msg name="description"> الوصف </msg>
<msg name="tools">الأدوات</msg>
<msg name="please_enter_a_valid_name"> الرجاء إدخال إسم صحيح! </msg>
<msg name="valid_name_instructions"> الرجاء إستعمال  ١٤ حرفاً و رقماً فقط. </msg>
<msg name="type_your_name_here"> أدخل(ي) إسمك </msg>
<msg name="ok"> إذهب(ي)! </msg>
<msg name="toggle_description_tooltip"> إضغط لإخفاء أو إظهار وصف ال ILS </msg>
<msg name="logout_label"> تسجيل الخروج </msg>
</messagebundle>